{
  "schemaVersion": "0.1",
  "idServer": {
    "dcs": "https://git.door43.org"
  },
  "identification": {
    "name": {
      "en": "unfoldingWord\u00ae Open Bible Stories"
    },
    "abbreviation": {
      "en": "ENOBS"
    },
    "description": {
      "en": "unrestricted visual Bible stories"
    },
    "systemId": {
      "dcs": {
        "id": "dcs::unfoldingword:en_obs",
        "revision": "94263a75308f91567c3c77ba862d53cbf6c80378"
      }
    }
  },
  "agencies": [
    {
      "name": {
        "en": "unfoldingWord"
      },
      "isRightsHolder": "true",
      "id": "dcs::unfoldingword",
      "abbr": "uW",
      "url": "https://www.unfoldingword.org",
      "contributes_content": true,
      "contributes_publication": true,
      "contributes_management": true,
      "contributes_finance": true,
      "contributes_qa": true
    }
  ],
  "languages": [
    {
      "name": {
        "en": "English"
      },
      "bcp47": "en",
      "scriptDirection": "LTR"
    }
  ],
  "countries": [
    {
      "name": {
        "en": "United States of America"
      },
      "iso": "US"
    }
  ],
  "type": {
    "flavor": "glossedTextStory",
    "flavorType": "gloss",
    "scope": [
      "GEN"
    ],
    "confidentiality": {
      "metadata": "unrestricted",
      "source": "private",
      "publications": "restricted"
    },
    "flavorDetails": {
      "storyVersion": "4.0.0"
    }
  },
  "ingredients": {
    "LICENSE.md": {
      "checksum": "7ccb0854d960c013e56608daa28e03ae",
      "mimeType": "text/markdown",
      "size": 1644
    },
    "content/01.md": {
      "checksum": "39e81428079f566e96a10827b1f57df5",
      "mimeType": "text/markdown",
      "scopeOrRole": "GEN 1-2",
      "size": 4398
    },
    "content/02.md": {
      "checksum": "a80540afea3591b6414c7a6d337348d2",
      "mimeType": "text/markdown",
      "scopeOrRole": "GEN 3",
      "size": 3685
    },
    "content/03.md": {
      "checksum": "fc6101f665da97002862cafed784de95",
      "mimeType": "text/markdown",
      "scopeOrRole": "GEN 6-8",
      "size": 4643
    },
    "content/04.md": {
      "checksum": "17ccaa819af588bd1830168c4dc73008",
      "mimeType": "text/markdown",
      "scopeOrRole": "GEN 11-15",
      "size": 3111
    },
    "content/05.md": {
      "checksum": "aa93ae1514903e4762c41a4799bded1e",
      "mimeType": "text/markdown",
      "scopeOrRole": "GEN 16-22",
      "size": 3190
    },
    "content/06.md": {
      "checksum": "a472c547a96f8969c268eb47062cd221",
      "mimeType": "text/markdown",
      "scopeOrRole": "GEN 24:1-25:26",
      "size": 1930
    },
    "content/07.md": {
      "checksum": "4b8f9a9bb0db9cd3e1f9ac314e5f2fec",
      "mimeType": "text/markdown",
      "scopeOrRole": "GEN 25:27-35:29",
      "size": 2773
    },
    "content/08.md": {
      "checksum": "31890f93882d9bb33a38e54b8a052cd4",
      "mimeType": "text/markdown",
      "scopeOrRole": "GEN 37-50",
      "size": 4021
    },
    "content/09.md": {
      "checksum": "ef11865205f3dac31d6ebd74859df859",
      "mimeType": "text/markdown",
      "scopeOrRole": "EXO 1-4",
      "size": 4075
    },
    "content/10.md": {
      "checksum": "6351fc1873ff37adb5a64d28aaed7b3f",
      "mimeType": "text/markdown",
      "scopeOrRole": "EXO 5-10",
      "size": 3127
    },
    "content/11.md": {
      "checksum": "0aa0b5d47463a09275946dcb69c6418b",
      "mimeType": "text/markdown",
      "scopeOrRole": "EXO 11:1-12:32",
      "size": 2176
    },
    "content/12.md": {
      "checksum": "8f068bb39642226608ad71c0880ee1fd",
      "mimeType": "text/markdown",
      "scopeOrRole": "EXO 12:33-15:21",
      "size": 4033
    },
    "content/13.md": {
      "checksum": "866e301050f63db4c03f0102f9e2a99e",
      "mimeType": "text/markdown",
      "scopeOrRole": "EXO 19-34",
      "size": 5005
    },
    "content/14.md": {
      "checksum": "69a1342da0c221a0ed115ec074db4079",
      "mimeType": "text/markdown",
      "scopeOrRole": "EXO 16-17;NUM 10-14;NUM 20;NUM 27;DEU 34",
      "size": 5562
    },
    "content/15.md": {
      "checksum": "ca3baee2d1bfa63d908e2e760b10a638",
      "mimeType": "text/markdown",
      "scopeOrRole": "JOS 1-24",
      "size": 4513
    },
    "content/16.md": {
      "checksum": "4428acfae6759887aa9c09fd7f6018f8",
      "mimeType": "text/markdown",
      "scopeOrRole": "JDG 1-3;JDG 6-8;1SA 1-10",
      "size": 6786
    },
    "content/17.md": {
      "checksum": "20a38a37f8728021824f41cb2dad8a08",
      "mimeType": "text/markdown",
      "scopeOrRole": "1SA 10;1SA 15-19;1SA 24;1SA 31;2SA 5;2SA 7;2SA 11-12",
      "size": 5657
    },
    "content/18.md": {
      "checksum": "c9662bbcdbbfbc6837d183827a4e6b62",
      "mimeType": "text/markdown",
      "scopeOrRole": "1KI 1-6;1KI 11-12",
      "size": 3878
    },
    "content/19.md": {
      "checksum": "84235401870e3d6535d2ff2645ffa7f6",
      "mimeType": "text/markdown",
      "scopeOrRole": "1KI 16-18;2KI 5;JER 38",
      "size": 6625
    },
    "content/20.md": {
      "checksum": "f0e84e54d7f12667082642dd8a960f21",
      "mimeType": "text/markdown",
      "scopeOrRole": "2KI 17;2KI 24-25;2CH 36;EZR 1-10;NEH 1-13",
      "size": 4428
    },
    "content/21.md": {
      "checksum": "8605b00d4108d814fee5b8bcfe72ea9a",
      "mimeType": "text/markdown",
      "scopeOrRole": "GEN 3:15;GEN 12:1-3;DEU 18:15;2SA 7;JER 31;ISA 59:16;DAN 7;MAL 4:5;ISA 7:14;MIC 5:2;ISA 9:1-7;ISA 35:3-5;ISA 61;ISA 53;PSA 22:18;PSA 35:19;PSA 69:4;PSA 41:9;ZEC 11:12-13;ISA 50:6;PSA 16:10-11",
      "size": 5781
    },
    "content/22.md": {
      "checksum": "0b1e7247f77b72208bfda33be83683a8",
      "mimeType": "text/markdown",
      "scopeOrRole": "LUK 1",
      "size": 2690
    },
    "content/23.md": {
      "checksum": "571077fc664ffb076428755896e544a7",
      "mimeType": "text/markdown",
      "scopeOrRole": "MAT 1;LUK 2",
      "size": 3468
    },
    "content/24.md": {
      "checksum": "1b45c927f704eabe9f135cdfbcdc48cd",
      "mimeType": "text/markdown",
      "scopeOrRole": "MAT 3;MRK 1:9-11;LUK 3:1-23",
      "size": 2620
    },
    "content/25.md": {
      "checksum": "5f5f9c220805cae0b0abf1d8a63f9b66",
      "mimeType": "text/markdown",
      "scopeOrRole": "MAT 4:1-11;MRK 1:12-13;LUK 4:1-13",
      "size": 1951
    },
    "content/26.md": {
      "checksum": "55f5e9b9bcc73f11696925b87b5c4cf7",
      "mimeType": "text/markdown",
      "scopeOrRole": "MAT 4:12-25;MRK 1:14-15,35-39;MRK 3:13-21;LUK 4:14-30,38-44",
      "size": 3495
    },
    "content/27.md": {
      "checksum": "eb55700953c0d59b1dc8b3cefb5bf887",
      "mimeType": "text/markdown",
      "scopeOrRole": "LUK 10:25-37",
      "size": 3028
    },
    "content/28.md": {
      "checksum": "fac5f8e09a83be6bb3ac094cccfa0e88",
      "mimeType": "text/markdown",
      "scopeOrRole": "MAT 19:16-30;MRK 10:17-31;LUK 18:18-30",
      "size": 2655
    },
    "content/29.md": {
      "checksum": "c5b79dd268d4b1ef89adb0dfea8c39f8",
      "mimeType": "text/markdown",
      "scopeOrRole": "MAT 18:21-35",
      "size": 2384
    },
    "content/30.md": {
      "checksum": "a7a5cfb0f51374b5a11868a46de54670",
      "mimeType": "text/markdown",
      "scopeOrRole": "MAT 14:13-21;MRK 6:31-44;LUK 9:10-17;JHN 6:5-15",
      "size": 2502
    },
    "content/31.md": {
      "checksum": "1bb93b0b3e253a5526e7d182588383f3",
      "mimeType": "text/markdown",
      "scopeOrRole": "MAT 14:22-33;MRK 6:45-52;JHN 6:16-21",
      "size": 2313
    },
    "content/32.md": {
      "checksum": "07190449c5cf01ed0871a84d4752f90c",
      "mimeType": "text/markdown",
      "scopeOrRole": "MAT 8:28-34;MAT 9:20-22;MRK 5:1-20;MRK 5:24-34;LUK 8:26-39;LUK 8:42-48",
      "size": 4293
    },
    "content/33.md": {
      "checksum": "a326a9334f697a282d02880d0f6e2eb9",
      "mimeType": "text/markdown",
      "scopeOrRole": "MAT 13:1-8,18-23;MRK 4:1-8,13-20;LUK 8:4-15",
      "size": 2766
    },
    "content/34.md": {
      "checksum": "4b220de9bb40ca55bcc93e271266c293",
      "mimeType": "text/markdown",
      "scopeOrRole": "MAT 13:31-33,44-46;MRK 4:30-32;LUK 13:18-21;LUK 18:9-14",
      "size": 2875
    },
    "content/35.md": {
      "checksum": "5e41ff2898098b9ff1cec9ecfc30f29d",
      "mimeType": "text/markdown",
      "scopeOrRole": "LUK 15:11-32",
      "size": 3638
    },
    "content/36.md": {
      "checksum": "d981f3aa3b4ae51a3250240ce908c653",
      "mimeType": "text/markdown",
      "scopeOrRole": "MAT 17:1-9;MRK 9:2-8;LUK 9:28-36",
      "size": 1933
    },
    "content/37.md": {
      "checksum": "0b997eb1b60f2216a12e93a4f117c13b",
      "mimeType": "text/markdown",
      "scopeOrRole": "JHN 11:1-46",
      "size": 3382
    },
    "content/38.md": {
      "checksum": "1db355a0f75a4e35a786f18f5dede91a",
      "mimeType": "text/markdown",
      "scopeOrRole": "MAT 26:14-56;MRK 14:10-50;LUK 22:1-53;JHN 12:6;JHN 18:1-11",
      "size": 4992
    },
    "content/39.md": {
      "checksum": "e96748e2901af86a2ff9ae0ff01474c2",
      "mimeType": "text/markdown",
      "scopeOrRole": "MAT 26:57-27:26;MRK 14:53-15:15;LUK 22:54-23:25;JHN 18:12-19:16",
      "size": 3864
    },
    "content/40.md": {
      "checksum": "6ffa1e657edbd93b250c578e94706ce2",
      "mimeType": "text/markdown",
      "scopeOrRole": "MAT 27:27-61;MRK 15:16-47;LUK 23:26-56;JHN 19:17-42",
      "size": 2952
    },
    "content/41.md": {
      "checksum": "10962702e8421cc15acebdb1bbdf6a39",
      "mimeType": "text/markdown",
      "scopeOrRole": "MAT 27:62-28:15;MRK 16:1-11;LUK 24:1-12;JHN 20:1-18",
      "size": 2515
    },
    "content/42.md": {
      "checksum": "ff6d7bf182430ec23e4fae1eb1962704",
      "mimeType": "text/markdown",
      "scopeOrRole": "MAT 28:16-20;MRK 16:12-20;LUK 24:13-53;JHN 20:19-23;ACT 1:1-11",
      "size": 4350
    },
    "content/43.md": {
      "checksum": "fd1dfc9f92944f8a5f407f6fa772a243",
      "mimeType": "text/markdown",
      "scopeOrRole": "ACT 2",
      "size": 3904
    },
    "content/44.md": {
      "checksum": "834e091cc7a8fb88e35e503c211be1ff",
      "mimeType": "text/markdown",
      "scopeOrRole": "ACT 3:1-4:22",
      "size": 2890
    },
    "content/45.md": {
      "checksum": "affbd3eb32ac61aff553e66ba38e81cb",
      "mimeType": "text/markdown",
      "scopeOrRole": "ACT 6:8-8:5;ACT 8:26-40",
      "size": 4598
    },
    "content/46.md": {
      "checksum": "4fb1899be870bdd3921a65c183db698a",
      "mimeType": "text/markdown",
      "scopeOrRole": "ACT 8:3;ACT 9:1-31;ACT 11:19-26;ACT 13:1-3",
      "size": 4026
    },
    "content/47.md": {
      "checksum": "9c6dac4664f8016851a065f8cb8729d5",
      "mimeType": "text/markdown",
      "scopeOrRole": "ACT 16:11-40",
      "size": 4244
    },
    "content/48.md": {
      "checksum": "de7945b281df514778aa0a6ff67a1b08",
      "mimeType": "text/markdown",
      "scopeOrRole": "GEN 1-3;GEN 6;GEN 14;GEN 22;EXO 12;EXO 20;2SA 7;HEB 3:1-6;HEB 4:14-5:10;HEB 7:1-8:13;HEB 9:11-10:18;REV 21",
      "size": 4926
    },
    "content/49.md": {
      "checksum": "5b754c297de6eeb82372d40f4cc9c16f",
      "mimeType": "text/markdown",
      "scopeOrRole": "ROM 3:21-26;ROM 5:1-11;JHN 3:16;MRK 16:16;COL 1:13-14;2CO 5:17-21;1JN 1:5-10",
      "size": 5677
    },
    "content/50.md": {
      "checksum": "277af7764af1bfc89302f21d5ff40e98",
      "mimeType": "text/markdown",
      "scopeOrRole": "MAT 24:14;MAT 28:18;JHN 15:20;JHN 16:33;REV 2:10;MAT 13:24-30;MAT 13,36-42;1TH 4:13-5:11;JAS 1:12;MAT 22:13;REV 20:10;REV 21:1-22:21",
      "size": 5942
    },
    "content/back.md": {
      "checksum": "18f7b1630de0d761ce4572a6e158c3ad",
      "mimeType": "text/markdown",
      "scopeOrRole": "pubdata",
      "size": 909
    },
    "content/front.md": {
      "checksum": "2de95f95a36868c91e0eb3c66671e007",
      "mimeType": "text/plain",
      "scopeOrRole": "title",
      "size": 35
    }
  },
  "licenses": [
    {
      "url": "https://creativecommons.org/licenses/by-sa/4.0/"
    }
  ],
  "copyright": [
    {
      "type": "full",
      "format": "plain",
      "lang": "en",
      "content": "Copyright \u00a9 2019 by unfoldingWord"
    }
  ],
  "snapshot": {
    "comments": "Version 4"
  }
}
